upytl_standard/__init__.py
upytl_standard/s_components.py
upytl_standard-0.0.2.dist-info/LICENSE
upytl_standard-0.0.2.dist-info/METADATA
upytl_standard-0.0.2.dist-info/WHEEL
upytl_standard-0.0.2.dist-info/top_level.txt
upytl_standard-0.0.2.dist-info/RECORD
